ProxyScrapeAsync/__init__.py
ProxyScrapeAsync-0.0.1.dist-info/METADATA
ProxyScrapeAsync-0.0.1.dist-info/WHEEL
ProxyScrapeAsync-0.0.1.dist-info/top_level.txt
ProxyScrapeAsync-0.0.1.dist-info/RECORD
