Metadata-Version: 2.1
Name: ProxyScrapeAsync
Version: 0.0.1
Summary: A Way Getting Proxies Easily. (Powered By ProxyScrape)
Author: Pirxcy
Classifier: Programming Language :: Python :: 3
Classifier: License :: OSI Approved :: MIT License
Classifier: Operating System :: OS Independent
Requires-Dist: aiohttp
